prosper_shared/__init__.py
prosper_shared/autohooks/__init__.py
prosper_shared/autohooks/assert_files.py
prosper_shared/autohooks/autoimport.py
prosper_shared/autohooks/build.py
prosper_shared/autohooks/build_extras.py
prosper_shared/autohooks/clean.py
prosper_shared/autohooks/dynamic_versioning.py
prosper_shared/autohooks/mdformat.py
prosper_shared/autohooks/mutmut.py
prosper_shared/autohooks/pydoclint.py
prosper_shared/autohooks/pydocstyle.py
prosper_shared/autohooks/tomlsort.py
prosper_shared/autohooks/tox.py
prosper_shared/autohooks/update_dependencies.py
prosper_shared/omni_config/__init__.py
prosper_shared/omni_config/_define.py
prosper_shared/omni_config/_merge.py
prosper_shared/omni_config/_parse.py
prosper_shared-0.8.4.dist-info/LICENSE
prosper_shared-0.8.4.dist-info/METADATA
prosper_shared-0.8.4.dist-info/WHEEL
prosper_shared-0.8.4.dist-info/entry_points.txt
prosper_shared-0.8.4.dist-info/RECORD
