Metadata-Version: 2.1
Name: prosper-shared
Version: 0.8.4
Summary: 
License: Apache 2.0
Author: Graham Tibbitts
Author-email: graham.tibbitts@gmail.com
Requires-Python: >=3.9,<4.0
Classifier: License :: OSI Approved :: Apache Software License
Classifier: License :: Other/Proprietary License
Classifier: Operating System :: OS Independent
Classifier: Programming Language :: Python :: 3
Classifier: Programming Language :: Python :: 3.9
Classifier: Programming Language :: Python :: 3.10
Classifier: Programming Language :: Python :: 3.11
Classifier: Programming Language :: Python :: 3 :: Only
Classifier: Programming Language :: Python :: 3.12
Classifier: Programming Language :: Python :: 3.8
Classifier: Topic :: Office/Business :: Financial :: Investment
Provides-Extra: dev
Provides-Extra: toml
Provides-Extra: yaml
Requires-Dist: autohooks (>=23.10.0,<24.0.0) ; extra == "dev"
Requires-Dist: autohooks-plugin-black (>=23.10.0,<24.0.0) ; extra == "dev"
Requires-Dist: autohooks-plugin-isort (>=23.10.0,<24.0.0) ; extra == "dev"
Requires-Dist: autohooks-plugin-pytest (>=23.10.0,<24.0.0) ; extra == "dev"
Requires-Dist: autohooks-plugin-ruff (>=23.11.0,<24.0.0) ; extra == "dev"
Requires-Dist: autoimport (>=1.3.3,<2.0.0) ; extra == "dev"
Requires-Dist: case-converter (>=1.1.0,<2.0.0)
Requires-Dist: deepmerge (>=1.1.0,<2.0.0)
Requires-Dist: dpath (>=2.1.6,<3.0.0)
Requires-Dist: jinja2-cli (>=0.8.2,<0.9.0) ; extra == "dev"
Requires-Dist: mdformat-gfm (>=0.3.5,<0.4.0) ; extra == "dev"
Requires-Dist: mutmut (>=2.4.4,<3.0.0) ; extra == "dev"
Requires-Dist: platformdirs (>=4.1.0,<5.0.0)
Requires-Dist: pydoclint (>=0.3.8,<0.4.0) ; extra == "dev"
Requires-Dist: pydocstyle (>=6.3.0,<7.0.0) ; extra == "dev"
Requires-Dist: pytest (>=7.4.2,<8.0.0) ; extra == "dev"
Requires-Dist: pytest-cov (>=4.1.0,<5.0.0) ; extra == "dev"
Requires-Dist: pytest-mock (>=3.11.1,<4.0.0) ; extra == "dev"
Requires-Dist: pytest-sugar (>=0.9.7,<0.10.0) ; extra == "dev"
Requires-Dist: pyyaml (>=6.0.1,<7.0.0) ; extra == "dev" or extra == "yaml"
Requires-Dist: schema (>=0.7.5,<0.8.0)
Requires-Dist: toml (>=0.10.2,<0.11.0) ; extra == "toml"
Requires-Dist: toml-sort (>=0.23.1,<0.24.0) ; extra == "dev"
Requires-Dist: tox (>=4.11.3,<5.0.0) ; extra == "dev"
